arcon/__init__.py
arcon/_version.py
arcon/py.typed
arcon-0.4.0.dist-info/LICENSE
arcon-0.4.0.dist-info/METADATA
arcon-0.4.0.dist-info/WHEEL
arcon-0.4.0.dist-info/RECORD
