Metadata-Version: 2.1
Name: arcon
Version: 0.4.0
Summary: Persistent runtime config
Home-page: https://pypi.org/project/arcon/
License: MIT
Keywords: arguments,config,params,parser,runtime
Author: jshwi
Author-email: stephen@jshwisolutions.com
Maintainer: jshwi
Maintainer-email: stephen@jshwisolutions.com
Requires-Python: >=3.8,<4.0
Classifier: License :: OSI Approved :: MIT License
Classifier: Programming Language :: Python :: 3
Classifier: Programming Language :: Python :: 3.8
Classifier: Programming Language :: Python :: 3.9
Classifier: Programming Language :: Python :: 3.10
Classifier: Programming Language :: Python :: 3.11
Classifier: Programming Language :: Python :: 3.12
Requires-Dist: mergedeep (>=1.3.4,<2.0.0)
Requires-Dist: tomli (>=2.0.1,<3.0.0)
Project-URL: Documentation, https://arcon.readthedocs.io/en/latest
Project-URL: Repository, https://github.com/jshwi/arcon
